uxspoilers.py
__pycache__/uxspoilers.cpython-311.opt-1.pyc
proxy.py_uxspoilers_plugin-2021.5.18.post4.dist-info/LICENSE
proxy.py_uxspoilers_plugin-2021.5.18.post4.dist-info/METADATA
proxy.py_uxspoilers_plugin-2021.5.18.post4.dist-info/WHEEL
proxy.py_uxspoilers_plugin-2021.5.18.post4.dist-info/top_level.txt
proxy.py_uxspoilers_plugin-2021.5.18.post4.dist-info/RECORD
