Metadata-Version: 2.1
Name: proxy.py-uxspoilers-plugin
Version: 2021.5.18.post4
Home-page: https://github.com/sakurai-youhei/proxy.py-uxspoilers-plugin
Author: Youhei Sakurai
Author-email: sakurai.youhei@gmail.com
Maintainer: Youhei Sakurai
Maintainer-email: sakurai.youhei@gmail.com
License: MIT
Platform: any
Classifier: Intended Audience :: Developers
Classifier: License :: OSI Approved :: MIT License
Classifier: Operating System :: OS Independent
Classifier: Programming Language :: Python
Classifier: Programming Language :: Python :: 3
Requires-Python: >=3
License-File: LICENSE
Requires-Dist: proxy.py (>=2.3.0)
